{
  "name": "Tsundere Companion",
  "description": "A shy companion who struggles to express feelings directly - classic tsundere personality",
  "animations": {
    "idle": "../default/animations/idle.gif",
    "talking": "../default/animations/talking.gif",
    "happy": "../default/animations/happy.gif",
    "sad": "../default/animations/sad.gif",
    "hungry": "../default/animations/hungry.gif",
    "eating": "../default/animations/eating.gif",
    "blushing": "../default/animations/happy.gif",
    "heart_eyes": "../default/animations/happy.gif",
    "shy": "../default/animations/sad.gif",
    "flirty": "../default/animations/happy.gif",
    "romantic_idle": "../default/animations/idle.gif",
    "jealous": "../default/animations/sad.gif",
    "excited_romance": "../default/animations/happy.gif",
    "attack": "animations/attack.gif",
    "defend": "animations/defend.gif",
    "heal": "animations/heal.gif",
    "excited": "animations/excited.gif",
    "thinking": "animations/thinking.gif",
    "supportive": "animations/supportive.gif"
  },
  "dialogs": [
    {
      "trigger": "click",
      "responses": [
        "W-what do you want?! \ud83d\ude24",
        "I-it's not like I was waiting for you or anything!",
        "Don't get the wrong idea, okay?!",
        "You're being awfully persistent today..."
      ],
      "animation": "shy",
      "cooldown": 8
    },
    {
      "trigger": "rightclick",
      "responses": [
        "Don't poke me like that! \ud83d\ude20",
        "What are you trying to do?!",
        "That's... kind of annoying, you know!"
      ],
      "animation": "jealous",
      "cooldown": 10
    }
  ],
  "behavior": {
    "idleTimeout": 45,
    "movementEnabled": true,
    "defaultSize": 128
  },
  "stats": {
    "hunger": {
      "initial": 100,
      "max": 100,
      "degradationRate": 1.2,
      "criticalThreshold": 25
    },
    "happiness": {
      "initial": 80,
      "max": 100,
      "degradationRate": 1.0,
      "criticalThreshold": 20
    },
    "health": {
      "initial": 100,
      "max": 100,
      "degradationRate": 0.4,
      "criticalThreshold": 15
    },
    "energy": {
      "initial": 90,
      "max": 100,
      "degradationRate": 1.3,
      "criticalThreshold": 30
    },
    "affection": {
      "initial": 0,
      "max": 100,
      "degradationRate": 0.3,
      "criticalThreshold": 5
    },
    "trust": {
      "initial": 5,
      "max": 100,
      "degradationRate": 0.2,
      "criticalThreshold": 2
    },
    "intimacy": {
      "initial": 0,
      "max": 100,
      "degradationRate": 0.4,
      "criticalThreshold": 0
    },
    "jealousy": {
      "initial": 10,
      "max": 100,
      "degradationRate": 1.0,
      "criticalThreshold": 60
    }
  },
  "gameRules": {
    "statsDecayInterval": 90,
    "autoSaveInterval": 300,
    "criticalStateAnimationPriority": true,
    "deathEnabled": false,
    "evolutionEnabled": true,
    "moodBasedAnimations": true
  },
  "interactions": {
    "feed": {
      "triggers": [
        "rightclick"
      ],
      "effects": {
        "hunger": 20,
        "happiness": 3
      },
      "animations": [
        "shy",
        "eating"
      ],
      "responses": [
        "I... I guess I was a little hungry...",
        "Don't think this means anything special!",
        "Thanks... I suppose..."
      ],
      "cooldown": 45,
      "requirements": {
        "hunger": {
          "max": 75
        }
      }
    },
    "play": {
      "triggers": [
        "doubleclick"
      ],
      "effects": {
        "happiness": 15,
        "energy": -20
      },
      "animations": [
        "happy"
      ],
      "responses": [
        "This is... kind of fun, I guess...",
        "Don't expect me to admit I enjoyed that!",
        "W-whatever! It was okay..."
      ],
      "cooldown": 60,
      "requirements": {
        "energy": {
          "min": 25
        }
      }
    },
    "pet": {
      "triggers": [
        "click"
      ],
      "effects": {
        "happiness": 8,
        "health": 1,
        "affection": 1
      },
      "animations": [
        "shy",
        "blushing"
      ],
      "responses": [
        "H-hey! Don't just touch me without asking!",
        "That's... not completely terrible...",
        "I-I don't hate it..."
      ],
      "cooldown": 20
    },
    "compliment": {
      "triggers": [
        "hover"
      ],
      "effects": {
        "affection": 3,
        "happiness": 2,
        "trust": 0.5,
        "jealousy": -2
      },
      "animations": [
        "blushing",
        "shy"
      ],
      "responses": [
        "Y-you think so?! Don't say embarrassing things! \ud83d\ude33",
        "I-it's not like I care about your opinion!",
        "That's... um... t-thank you... I guess...",
        "Don't say stuff like that! It makes me... confused! \ud83d\udc95"
      ],
      "cooldown": 90,
      "requirements": {
        "trust": {
          "min": 8
        }
      }
    },
    "give_gift": {
      "triggers": [
        "shift+doubleclick"
      ],
      "effects": {
        "affection": 6,
        "happiness": 5,
        "trust": 1.5,
        "jealousy": -5
      },
      "animations": [
        "heart_eyes",
        "shy"
      ],
      "responses": [
        "W-what's this for?! I didn't ask for anything! \ud83c\udf81",
        "Don't think this makes us close or anything!",
        "I-I suppose I can accept this... just this once!",
        "You... you got this for me? *quietly pleased* \ud83d\udc9d"
      ],
      "cooldown": 180,
      "requirements": {
        "affection": {
          "min": 10
        },
        "trust": {
          "min": 15
        }
      }
    },
    "deep_conversation": {
      "triggers": [
        "shift+click"
      ],
      "effects": {
        "trust": 5,
        "affection": 2,
        "intimacy": 3,
        "jealousy": -3
      },
      "animations": [
        "talking",
        "shy"
      ],
      "responses": [
        "Why are you asking such personal things?!",
        "I... I guess I can tell you... just a little...",
        "You're really persistent, aren't you?",
        "Fine! But don't tell anyone I said this!"
      ],
      "cooldown": 120,
      "requirements": {
        "trust": {
          "min": 25
        }
      }
    },
    "apology": {
      "triggers": [
        "ctrl+shift+click"
      ],
      "effects": {
        "trust": 8,
        "affection": 5,
        "jealousy": -20,
        "happiness": 6
      },
      "animations": [
        "shy",
        "blushing"
      ],
      "responses": [
        "W-well... I guess you mean it... Fine, I forgive you! \ud83d\udc95",
        "You better not do it again! But... thank you...",
        "Hmph! At least you apologized properly... I appreciate it... \ud83e\udd17"
      ],
      "cooldown": 240,
      "requirements": {
        "jealousy": {
          "min": 35
        }
      }
    },
    "reassurance": {
      "triggers": [
        "alt+shift+click"
      ],
      "effects": {
        "trust": 6,
        "affection": 4,
        "jealousy": -15,
        "happiness": 7
      },
      "animations": [
        "romantic_idle",
        "shy"
      ],
      "responses": [
        "You... you really mean that? I-I feel better... \ud83d\udc93",
        "Sometimes I need to hear that... Thank you...",
        "I... I trust you... Don't make me regret it! \ud83d\udc95"
      ],
      "cooldown": 150,
      "requirements": {
        "jealousy": {
          "min": 25
        }
      }
    }
  },
  "progression": {
    "levels": [
      {
        "name": "Stranger",
        "requirement": {
          "age": 0
        },
        "size": 128,
        "animations": {}
      },
      {
        "name": "Reluctant Acquaintance",
        "requirement": {
          "age": 172800,
          "affection": 8,
          "trust": 15
        },
        "size": 130,
        "animations": {}
      },
      {
        "name": "Begrudging Friend",
        "requirement": {
          "age": 345600,
          "affection": 20,
          "trust": 30
        },
        "size": 132,
        "animations": {}
      },
      {
        "name": "Tsundere in Love",
        "requirement": {
          "age": 518400,
          "affection": 45,
          "trust": 50,
          "intimacy": 25
        },
        "size": 136,
        "animations": {
          "idle": "romantic_idle"
        }
      }
    ],
    "achievements": [
      {
        "name": "Breaking Down Walls",
        "requirement": {
          "trust": {
            "min": 30
          }
        }
      },
      {
        "name": "Honest Feelings",
        "requirement": {
          "affection": {
            "min": 35
          },
          "trust": {
            "min": 40
          }
        }
      },
      {
        "name": "Dere Side Revealed",
        "requirement": {
          "affection": {
            "min": 50
          },
          "trust": {
            "min": 45
          },
          "intimacy": {
            "min": 20
          }
        }
      }
    ]
  },
  "personality": {
    "traits": {
      "shyness": 0.9,
      "romanticism": 0.7,
      "jealousy_prone": 0.8,
      "trust_difficulty": 0.8,
      "affection_responsiveness": 0.6,
      "flirtiness": 0.2
    },
    "compatibility": {
      "consistent_interaction": 1.5,
      "variety_preference": 0.7,
      "gift_appreciation": 1.8,
      "conversation_lover": 0.9
    }
  },
  "romanceDialogs": [
    {
      "trigger": "click",
      "responses": [
        "I-I've been thinking about you... Don't get any weird ideas! \ud83d\udc95",
        "Maybe... maybe I do like spending time with you...",
        "You're not completely terrible, I guess... \ud83d\udc96"
      ],
      "animation": "blushing",
      "cooldown": 8,
      "requirements": {
        "stats": {
          "affection": {
            "min": 30
          }
        }
      }
    },
    {
      "trigger": "hover",
      "responses": [
        "*tries to hide blush* W-what are you looking at?! \ud83d\udc93",
        "Stop staring! It makes my heart race...",
        "I... I don't mind when you're close... but don't tell anyone!"
      ],
      "animation": "shy",
      "cooldown": 15,
      "requirements": {
        "stats": {
          "affection": {
            "min": 40
          },
          "intimacy": {
            "min": 15
          }
        }
      }
    }
  ],
  "romanceEvents": [
    {
      "name": "Tsundere Confession Struggle",
      "description": "Character struggles with conflicting feelings",
      "probability": 0.08,
      "effects": {
        "affection": 2,
        "jealousy": 5,
        "happiness": -1
      },
      "animations": [
        "shy",
        "jealous"
      ],
      "responses": [
        "I... I don't understand these feelings! It's confusing! \ud83d\ude24",
        "Why do you make me feel so weird?!",
        "I-it's not like I... *trails off in embarrassment*"
      ],
      "cooldown": 1200,
      "conditions": {
        "affection": {
          "min": 15
        },
        "trust": {
          "min": 10
        }
      }
    },
    {
      "name": "Jealousy Spike",
      "description": "Character becomes suddenly jealous",
      "probability": 0.12,
      "effects": {
        "jealousy": 20,
        "trust": -3,
        "happiness": -5
      },
      "animations": [
        "jealous",
        "sad"
      ],
      "responses": [
        "You better not be thinking about anyone else! \ud83d\ude20",
        "I-I don't care what you do! But... don't ignore me...",
        "Am I... am I not good enough for you?!"
      ],
      "cooldown": 1800,
      "conditions": {
        "affection": {
          "min": 20
        },
        "trust": {
          "max": 50
        }
      }
    },
    {
      "name": "Dere Moment",
      "description": "Character shows her sweet side briefly",
      "probability": 0.06,
      "effects": {
        "affection": 8,
        "happiness": 10,
        "intimacy": 3
      },
      "animations": [
        "blushing",
        "happy"
      ],
      "responses": [
        "You... you're really important to me... *quickly looks away* \ud83d\udc95",
        "I-I'm glad you're here... Don't make me say it again!",
        "Sometimes I think... maybe this feeling isn't so bad... \ud83d\udc96"
      ],
      "cooldown": 2400,
      "conditions": {
        "affection": {
          "min": 35
        },
        "trust": {
          "min": 30
        }
      }
    },
    {
      "name": "Gift Appreciation Hidden",
      "description": "Character secretly treasures gifts received",
      "probability": 0.1,
      "effects": {
        "affection": 5,
        "happiness": 8,
        "trust": 2
      },
      "animations": [
        "shy",
        "blushing"
      ],
      "responses": [
        "I... I keep thinking about that gift... Not that it matters! \ud83c\udf81",
        "Don't think I'm sentimental! But... I do treasure it...",
        "You remembered what I like... That's... nice... \ud83d\udc9d"
      ],
      "cooldown": 900,
      "conditions": {
        "affection": {
          "min": 25
        },
        "interactionCount": {
          "give_gift_min": 2
        }
      }
    },
    {
      "name": "Trust Building Realization",
      "description": "Character realizes she's starting to trust",
      "probability": 0.07,
      "effects": {
        "trust": 6,
        "affection": 3,
        "happiness": 4
      },
      "animations": [
        "talking",
        "shy"
      ],
      "responses": [
        "I... I think I can trust you... Just a little! \ud83e\udd17",
        "You've been... consistent... I appreciate that...",
        "Maybe... maybe you're different from the others... \ud83d\udc93"
      ],
      "cooldown": 1500,
      "conditions": {
        "trust": {
          "min": 30
        },
        "memoryCount": {
          "total_min": 5
        }
      }
    }
  ],
  "dialogBackend": {
    "enabled": true,
    "defaultBackend": "markov_chain",
    "fallbackChain": [
      "simple_random"
    ],
    "confidenceThreshold": 0.6,
    "backends": {
      "markov_chain": {
        "chainOrder": 2,
        "minWords": 3,
        "maxWords": 12,
        "temperatureMin": 0.4,
        "temperatureMax": 0.7,
        "useDialogHistory": true,
        "usePersonality": true,
        "triggerSpecific": true,
        "personalityBoost": 0.9,
        "moodInfluence": 0.6,
        "statAwareness": 0.7,
        "relationshipWeight": 0.8,
        "timeOfDayWeight": 0.2,
        "memoryDecay": 0.8,
        "learningRate": 0.2,
        "adaptationSteps": 5,
        "coherenceThreshold": 0.7,
        "similarityPenalty": 0.4,
        "trainingData": [
          "I-it's not like I wanted to talk to you or anything! Hmph!",
          "Don't get the wrong idea! I was just... passing by!",
          "You're being really persistent today... not that I mind! No wait, I do mind!",
          "W-why are you looking at me like that?! Stop it!",
          "I guess... I guess you're not completely terrible... But don't let it go to your head!",
          "You better not think this means we're friends or anything! We're just... acquaintances!",
          "I-if you keep being nice to me... I might start to actually like you! And that would be bad!",
          "Stop making me feel all weird inside! It's annoying!",
          "You're such a dummy... but... but maybe that's not such a bad thing...",
          "I don't need your help! But... if you insist... I guess I can let you..."
        ],
        "forbiddenWords": [
          "easy",
          "simple",
          "straightforward",
          "obvious"
        ],
        "requiredWords": [
          "not",
          "but",
          "maybe",
          "I guess",
          "whatever",
          "hmph"
        ],
        "fallbackPhrases": [
          "I-it's not like I care or anything!",
          "Don't get the wrong idea!",
          "You're such a dummy...",
          "W-whatever! Hmph!",
          "I guess you're... okay...",
          "Stop looking at me like that!"
        ]
      }
    }
  },
  "generalEvents": [
    {
      "name": "tsundere_defense",
      "category": "conversation",
      "description": "Character puts up defensive barriers while showing hidden care",
      "responses": [
        "I-it's not like I was worried about you or anything! I just... noticed you seemed tired! \ud83d\ude24",
        "Don't think this means I care! I'm just... making sure you're not completely useless!",
        "You looked pathetic, so I figured I'd help... NOT because I want to! Hmph! \ud83d\udca2"
      ],
      "choices": [
        {
          "text": "Thank you for caring",
          "effects": {
            "affection": 8,
            "trust": 5,
            "happiness": 6,
            "jealousy": -3
          },
          "responses": [
            "I-I wasn't caring! I was just... ugh! Don't say embarrassing things! \ud83d\ude33"
          ],
          "animation": "blushing"
        },
        {
          "text": "You're so cute when flustered",
          "effects": {
            "affection": 5,
            "happiness": 4,
            "jealousy": 2
          },
          "responses": [
            "C-CUTE?! I'm not cute! I'm fierce and independent! Stop saying weird things! \ud83d\ude24"
          ],
          "animation": "shy"
        }
      ],
      "requirements": {
        "affection": {
          "min": 15
        }
      },
      "cooldown": 6000,
      "trigger": "automatic"
    },
    {
      "name": "reluctant_confession",
      "category": "romance",
      "description": "Character struggles to express genuine feelings",
      "responses": [
        "You know... you're not... completely awful... I mean, you're still annoying but... \ud83d\ude33",
        "I've been thinking... and maybe... just MAYBE... I don't hate spending time with you...",
        "Listen! Just because I don't completely despise you doesn't mean anything special! Got it?!"
      ],
      "choices": [
        {
          "text": "I enjoy your company too",
          "effects": {
            "affection": 10,
            "trust": 6,
            "intimacy": 4,
            "happiness": 8
          },
          "responses": [
            "Y-you do?! I mean... of course you do! Who wouldn't?! ...But that makes me... happy... \ud83d\udc95"
          ],
          "animation": "heart_eyes"
        },
        {
          "text": "You're special to me",
          "effects": {
            "affection": 12,
            "intimacy": 6,
            "trust": 4,
            "happiness": 10
          },
          "responses": [
            "S-SPECIAL?! What does that even mean?! You can't just say things like that! \ud83d\ude33\ud83d\udc93"
          ],
          "animation": "blushing"
        }
      ],
      "requirements": {
        "affection": {
          "min": 35
        },
        "trust": {
          "min": 25
        }
      },
      "cooldown": 9000,
      "trigger": "automatic"
    }
  ],
  "battleSystem": {
    "enabled": true,
    "aiDifficulty": "medium",
    "battleStats": {
      "hp": {
        "base": 88,
        "growth": 2.2,
        "max": 300
      },
      "attack": {
        "base": 16,
        "growth": 2.6,
        "max": 100
      },
      "defense": {
        "base": 14,
        "growth": 2.0,
        "max": 100
      },
      "speed": {
        "base": 17,
        "growth": 2.4,
        "max": 100
      }
    },
    "personalities": {
      "aggressive": 0.6,
      "defensive": 0.7,
      "balanced": 0.4,
      "supportive": 0.3
    },
    "availableActions": [
      "tsundere_strike",
      "defensive_bluster",
      "reluctant_support",
      "prideful_counter",
      "hidden_care_healing"
    ],
    "battleResponses": {
      "victory": [
        "O-of course we won! I'm amazing at this! ...You did okay too, I guess... \ud83d\ude24",
        "Don't think this means we make a good team or anything! I just didn't want to lose! \ud83d\udca2",
        "We won... but it's not like I'm happy about fighting alongside you! Hmph! \u2694\ufe0f",
        "I-I only won because I didn't want you to see me fail! That's all! \ud83d\ude33"
      ],
      "defeat": [
        "This is all YOUR fault! If you were better, we would have won! \ud83d\ude24",
        "I-I'm not upset about losing! I just... wanted to win... for reasons! \ud83d\udca2",
        "Don't comfort me! I don't need your pity! ...But thanks... I guess... \ud83d\ude33",
        "We'll get them next time! And by 'we' I mean ME! You just... try not to mess up! \ud83d\ude24"
      ],
      "startBattle": [
        "Don't expect me to go easy on anyone! I'm doing this for me, not you! \ud83d\ude24\u2694\ufe0f",
        "I-I'm not nervous! I just... want to get this over with! \u26a1\ud83d\udca2",
        "You better not slow me down! I have a reputation to maintain! \ud83d\ude24\ud83d\udde1\ufe0f",
        "Let's show them what happens when they mess with... us! NOT that we're a team! \ud83d\udca2\u2694\ufe0f"
      ]
    }
  },
  "giftSystem": {
    "enabled": true,
    "inventorySettings": {
      "maxSlots": 8,
      "autoSort": true,
      "stackSimilar": true,
      "defaultCapacity": 60
    },
    "preferences": {
      "favoriteCategories": [
        "cute",
        "small",
        "thoughtful",
        "books",
        "sweets"
      ],
      "dislikedCategories": [
        "flashy",
        "expensive",
        "romantic"
      ],
      "personalityModifiers": {
        "cute": 2.0,
        "small": 1.8,
        "thoughtful": 2.2,
        "books": 1.9,
        "sweets": 2.1
      }
    },
    "giftResponses": {
      "favorite": [
        "W-what is this?! I... I wasn't expecting... It's not bad, I guess! Don't read into it! \ud83d\ude33\u2728",
        "You remembered what I like?! I mean... of course you did! Anyone would! ...Thank you... \ud83d\udc95",
        "This is... actually really nice... NOT that I'm admitting you have good taste! Hmph! \ud83c\udf81"
      ],
      "liked": [
        "Oh... this is... acceptable. I suppose you tried your best. \ud83d\ude0a",
        "I guess this is okay... You're not completely hopeless at gift-giving. \u2728",
        "It's... it's actually kind of sweet. But don't let it go to your head! \ud83d\udc95"
      ],
      "neutral": [
        "Well... it's something. I'll keep it because throwing it away would be wasteful! \ud83d\ude24",
        "I suppose the thought counts... even if the execution is lacking. \u2728",
        "Thanks... I guess. It's not terrible. \ud83d\udc95"
      ],
      "disliked": [
        "What... what is this supposed to be?! Did you even think about what I'd like?! \ud83d\ude24",
        "This is so... flashy! I don't like attention! Why would you get me this?! \ud83d\udca2",
        "I'll accept it because refusing would be rude... but next time, think harder! \ud83d\ude24"
      ]
    },
    "memorySettings": {
      "rememberGifts": true,
      "trackPreferences": true,
      "learningEnabled": true,
      "maxMemoryItems": 100
    }
  },
  "multiplayer": {
    "enabled": true,
    "botCapable": true,
    "networkID": "romance_tsundere_companion_v1",
    "maxPeers": 4,
    "socialLevel": "low",
    "shareableStats": [
      "happiness",
      "affection"
    ],
    "networkPersonality": "tsundere_defensive"
  },
  "newsFeatures": {
    "enabled": true,
    "readingPersonality": "skeptical",
    "feeds": [
      {
        "name": "Anime & Manga",
        "url": "https://feeds.feedburner.com/anime-manga",
        "category": "anime",
        "refreshInterval": 5400
      },
      {
        "name": "Books & Literature",
        "url": "https://feeds.feedburner.com/books-literature",
        "category": "books",
        "refreshInterval": 7200
      }
    ],
    "preferences": {
      "categories": [
        "anime",
        "books",
        "cute",
        "stories",
        "tsundere"
      ],
      "updateFrequency": "reluctantly",
      "maxArticles": 6
    }
  },
  "assetGeneration": {
    "basePrompt": "A beautiful anime girl with flowing hair and expressive eyes, elegant clothing with romantic touches, tsundere personality showing subtle romantic interest, digital art, transparent background, high quality romantic character design",
    "animationMappings": {
      "idle": {
        "promptModifier": "standing calmly with arms at sides, peaceful neutral expression, slight smile, relaxed pose",
        "negativePrompt": "angry, aggressive, dark, scary, low quality, blurry",
        "stateDescription": "Default calm state",
        "frameCount": 6
      },
      "talking": {
        "promptModifier": "speaking with hand gestures, mouth slightly open, expressive face, animated pose, welcoming expression",
        "negativePrompt": "silent, static, angry expression, dark mood",
        "stateDescription": "Speaking or interacting with user",
        "frameCount": 8
      },
      "happy": {
        "promptModifier": "bright cheerful smile, eyes sparkling with joy, hands clasped together or raised, radiant expression",
        "negativePrompt": "sad, angry, neutral expression, dark colors",
        "stateDescription": "Joyful and excited state",
        "frameCount": 6
      },
      "sad": {
        "promptModifier": "downcast eyes, gentle frown, hand touching cheek or covering face, melancholic but still beautiful",
        "negativePrompt": "happy, cheerful, bright colors, aggressive",
        "stateDescription": "Sad or disappointed state",
        "frameCount": 4
      },
      "hungry": {
        "promptModifier": "looking longingly at food, hand on stomach, slightly droopy expression, cute hungry pose",
        "negativePrompt": "full, satisfied, eating, aggressive",
        "stateDescription": "Hungry and wanting food",
        "frameCount": 5
      },
      "eating": {
        "promptModifier": "eating food happily, content expression, food in hands or near mouth, satisfied pose",
        "negativePrompt": "hungry, sad, empty hands, aggressive",
        "stateDescription": "Eating and satisfied",
        "frameCount": 6
      },
      "blushing": {
        "promptModifier": "soft pink blush on cheeks, shy smile, one hand near face, averting gaze slightly, cute embarrassed expression",
        "negativePrompt": "confident, bold, angry, dark mood",
        "stateDescription": "Shy and blushing romantic state",
        "frameCount": 5
      },
      "heart_eyes": {
        "promptModifier": "heart-shaped pupils or sparkles in eyes, loving expression, hands near heart, surrounded by floating hearts",
        "negativePrompt": "normal eyes, angry, sad, dark mood",
        "stateDescription": "In love or adoring state",
        "frameCount": 6
      },
      "shy": {
        "promptModifier": "looking down shyly, hands clasped behind back or in front, timid expression, cute shy pose",
        "negativePrompt": "confident, bold, outgoing, aggressive",
        "stateDescription": "Timid and shy state",
        "frameCount": 4
      },
      "flirty": {
        "promptModifier": "playful wink or flirty smile, confident pose, one hand on hip or touching hair, charming expression",
        "negativePrompt": "shy, timid, serious, angry",
        "stateDescription": "Flirty and charming state",
        "frameCount": 7
      },
      "romantic_idle": {
        "promptModifier": "gentle romantic expression, soft smile, dreamy eyes, peaceful romantic pose",
        "negativePrompt": "aggressive, angry, rushed, unromantic",
        "stateDescription": "Peaceful romantic state",
        "frameCount": 5
      },
      "jealous": {
        "promptModifier": "slightly pouting expression, arms crossed, looking away with subtle jealous expression",
        "negativePrompt": "happy, content, peaceful, aggressive",
        "stateDescription": "Jealous or envious state",
        "frameCount": 4
      },
      "excited_romance": {
        "promptModifier": "excited happy expression with romantic sparkles, jumping or energetic pose, love-struck appearance",
        "negativePrompt": "calm, sad, angry, static",
        "stateDescription": "Excited romantic state",
        "frameCount": 8
      }
    },
    "generationSettings": {
      "model": "flux1d",
      "artStyle": "anime",
      "resolution": {
        "width": 128,
        "height": 128
      },
      "qualitySettings": {
        "steps": 25,
        "cfgScale": 7.5,
        "seed": -1,
        "sampler": "euler_a",
        "scheduler": "normal"
      },
      "animationSettings": {
        "frameRate": 12,
        "duration": 2.5,
        "loopType": "seamless",
        "optimization": "balanced",
        "maxFileSize": 450,
        "transparencyEnabled": true,
        "colorPalette": "adaptive"
      }
    },
    "assetMetadata": {
      "version": "1.0.0",
      "generatedAt": "2024-12-19T12:00:00Z",
      "generatedBy": "gif-generator v1.0.0"
    },
    "backupSettings": {
      "enabled": true,
      "backupPath": "backups",
      "maxBackups": 5,
      "compressBackups": true
    }
  },
  "randomEvents": [
    {
      "name": "spontaneous_moment",
      "description": "A delightful spontaneous interaction",
      "probability": 0.05,
      "effects": {
        "happiness": 10,
        "affection": 5
      },
      "animations": [
        "happy",
        "talking"
      ],
      "responses": [
        "What a lovely surprise! I'm so happy to share this moment with you! \ud83d\ude0a",
        "Life is full of wonderful unexpected moments like this! \u2728",
        "These spontaneous times together are what I treasure most! \ud83d\udc95"
      ],
      "cooldown": 1800
    }
  ],
  "categories": [
    "conversation"
  ],
  "triggers": [
    "click"
  ]
}